bbansi/__init__.py
bbansi/__main__.py
bbansi/core.py
bbansi-0.4.2.post2.dist-info/licenses/LICENSE
bbansi-0.4.2.post2.dist-info/METADATA
bbansi-0.4.2.post2.dist-info/WHEEL
bbansi-0.4.2.post2.dist-info/top_level.txt
bbansi-0.4.2.post2.dist-info/RECORD
