Metadata-Version: 2.4
Name: bbansi
Version: 0.4.2.post2
Summary: Module with print and input that convert pseudo-BBCode into ANSI. It also includes a flip option that improves the .capitalize(), .lower(), .title(), and .upper() methods, and adds an invert option.
Author: Pablo Alejandro Carravetti
License: GNU General Public License v3.0
Classifier: Programming Language :: Python :: 3
Classifier: Operating System :: OS Independent
Requires-Python: >=3.9
License-File: LICENSE
Dynamic: license-file
